louvain.libs/libgomp-d22c30c5.so.1.0.0
louvain-0.8.2.dist-info/RECORD
louvain-0.8.2.dist-info/WHEEL
louvain-0.8.2.dist-info/METADATA
louvain-0.8.2.dist-info/top_level.txt
louvain-0.8.2.dist-info/LICENSE
louvain/functions.py
louvain/_c_louvain.cpython-310-aarch64-linux-gnu.so
louvain/VertexPartition.py
louvain/__init__.py
louvain/version.py
louvain/Optimiser.py
